codehackingcalculator_ARJ/__init__.py
codehackingcalculator_ARJ-0.1.dist-info/LICENSE.txt
codehackingcalculator_ARJ-0.1.dist-info/METADATA
codehackingcalculator_ARJ-0.1.dist-info/WHEEL
codehackingcalculator_ARJ-0.1.dist-info/top_level.txt
codehackingcalculator_ARJ-0.1.dist-info/RECORD
