Metadata-Version: 2.1
Name: codehackingcalculator-ARJ
Version: 0.1
Summary: basic calculator
Author: ARHAM JAIN
Author-email: jainarham724@gmail.com
Classifier: Programming Language :: Python :: 3
Classifier: License :: OSI Approved :: MIT License
Classifier: Operating System :: OS Independent
License-File: LICENSE.txt
